PythonSoundPlayerX/__init__.py
PythonSoundPlayerX/player.py
PythonSoundPlayerX/utils.py
pythonsoundplayerx-0.1.dist-info/METADATA
pythonsoundplayerx-0.1.dist-info/WHEEL
pythonsoundplayerx-0.1.dist-info/top_level.txt
pythonsoundplayerx-0.1.dist-info/RECORD
