Metadata-Version: 2.4
Name: PythonSoundPlayerX
Version: 0.1
Summary: Python 3.13 uyumlu sessiz mp3/wav oynatici kutuphane
Home-page: https://github.com/ruzgar/PythonSoundPlayerX
Author: Ruzgar
Classifier: Programming Language :: Python :: 3
Classifier: Operating System :: OS Independent
Requires-Python: >=3.6
Requires-Dist: pygame
Dynamic: author
Dynamic: classifier
Dynamic: description
Dynamic: description-content-type
Dynamic: home-page
Dynamic: requires-dist
Dynamic: requires-python
Dynamic: summary
